abm/VERSION
abm/__init__.py
abm/__main__.py
abm/lib/__init__.py
abm/lib/benchmark.py
abm/lib/cloudlaunch.py
abm/lib/common.py
abm/lib/config.py
abm/lib/dataset.py
abm/lib/experiment.py
abm/lib/folder.py
abm/lib/helm.py
abm/lib/histories.yml
abm/lib/history.py
abm/lib/invocation.py
abm/lib/job.py
abm/lib/kubectl.py
abm/lib/library.py
abm/lib/menu.yml
abm/lib/users.py
abm/lib/workflow.py
test/ThreadPoolTests.py
test/__init__.py
test/args.py
test/average.py
test/check_tools.py
test/lambda_test.py
test/metrics.py
test/test_environments.py
test/workflow.py
gxabm-2.10.0.dist-info/LICENSE
gxabm-2.10.0.dist-info/METADATA
gxabm-2.10.0.dist-info/WHEEL
gxabm-2.10.0.dist-info/entry_points.txt
gxabm-2.10.0.dist-info/top_level.txt
gxabm-2.10.0.dist-info/RECORD
