Metadata-Version: 2.1
Name: gxabm
Version: 2.10.0
Summary: Opinionated Benchmarking Automatation in Galaxy
Home-page: https://github.com/galaxyproject/gxabm
Author: Keith Suderman
Author-email: suderman@jhu.edu
License: MIT
Classifier: License :: OSI Approved :: MIT License
Classifier: Programming Language :: Python :: 3
Classifier: Programming Language :: Python :: 3.9
License-File: LICENSE
Requires-Dist: pathlib
Requires-Dist: bioblend
Requires-Dist: pyyaml
Requires-Dist: planemo
Requires-Dist: cloudlaunch-cli
